setup.cfg
setup.py
infpy/LICENSE
infpy/README
infpy/VERSION
infpy/__init__.py
infpy/bootstrap.py
infpy/convergence_test.py
infpy/distribution.py
infpy/roc.py
infpy/types.py
infpy/utils.py
infpy.egg-info/PKG-INFO
infpy.egg-info/SOURCES.txt
infpy.egg-info/dependency_links.txt
infpy.egg-info/requires.txt
infpy.egg-info/top_level.txt
infpy/dbn/__init__.py
infpy/dbn/harmonium.py
infpy/dbn/rbm.py
infpy/decision/__init__.py
infpy/decision/attributes.py
infpy/decision/decision.py
infpy/decision/genepy_interface.py
infpy/decision/rule_generation.py
infpy/decision/test/__init__.py
infpy/decision/test/decision_test.py
infpy/decision/test/genepy_test.py
infpy/decision/test/rule_test.py
infpy/dp/__init__.py
infpy/dp/gen_artificial_data.py
infpy/dp/infinite_multinomials.py
infpy/dp/hdpm/__init__.py
infpy/dp/hdpm/math.py
infpy/dp/hdpm/summarise.py
infpy/dp/hdpm/utils.py
infpy/dp/hdpm/uncertainty/__init__.py
infpy/dp/hdpm/uncertainty/summarise.py
infpy/exp/__init__.py
infpy/exp/test/__init__.py
infpy/exp/test/exp_family_test.py
infpy/genepy/__init__.py
infpy/genepy/population.py
infpy/gp/__init__.py
infpy/gp/feature_kernel.py
infpy/gp/gaussian_process.py
infpy/gp/gp_examples.py
infpy/gp/kernel.py
infpy/gp/kernel_short_names.py
infpy/gp/matern_kernel.py
infpy/gp/neural_network_kernel.py
infpy/gp/periodic_kernel.py
infpy/gp/piecewise_poly_kernel.py
infpy/gp/pre_calculated_kernel.py
infpy/gp/rational_quadratic_kernel.py
infpy/gp/real_kernel.py
infpy/gp/se_kernel.py
infpy/gp/sum_kernel.py
infpy/gp/test/__init__.py
infpy/gp/test/gp_test.py
infpy/gp/test/kernel_test.py
infpy/madbayes/__init__.py
infpy/madbayes/dpmeans.py
infpy/madbayes/test/__init__.py
infpy/mixture/__init__.py
infpy/mixture/beta.py
infpy/mixture/test/__init__.py
infpy/mixture/test/beta_test.py
infpy/test/__init__.py
infpy/test/distribution_test.py
infpy/test/roc_test.py
infpy/test/utils_test.py
infpy/variational/__init__.py
infpy/variational/dirichlet_process.py
infpy/variational/message_passing/__init__.py
infpy/variational/message_passing/factorised_variational.py
infpy/variational/message_passing/svmp.py
infpy/variational/message_passing/vmp.py
