Metadata-Version: 1.1
Name: infpy
Version: 0.4.13
Summary: A python inference library
Home-page: http://sysbio.mrc-bsu.cam.ac.uk/johns/infpy/docs/build/html/
Author: John Reid
Author-email: johnbaronreid@netscape.net
License: BSD
Keywords: Inference probabilistic models Gaussian processes Dirichlet processes
Platform: UNKNOWN
Classifier: Development Status :: 5 - Production/Stable
Classifier: Topic :: Utilities
Classifier: License :: OSI Approved :: BSD License
